stormshield/__init__.py
stormshield/sns/__init__.py
stormshield/sns/bundle.ca
stormshield/sns/cli.py
stormshield/sns/cmd.complete
stormshield/sns/configparser.py
stormshield/sns/crc.py
stormshield/sns/sslclient/__init__.py
stormshield/sns/sslclient/__version__.py
stormshield.sns.sslclient-1.1.0.dist-info/LICENCE
stormshield.sns.sslclient-1.1.0.dist-info/METADATA
stormshield.sns.sslclient-1.1.0.dist-info/WHEEL
stormshield.sns.sslclient-1.1.0.dist-info/entry_points.txt
stormshield.sns.sslclient-1.1.0.dist-info/top_level.txt
stormshield.sns.sslclient-1.1.0.dist-info/RECORD
