Metadata-Version: 2.1
Name: stormshield.sns.sslclient
Version: 1.1.0
Summary: SSL API client for Stormshield Network Security appliances
Home-page: https://github.com/stormshield/python-SNS-API
Author: Remi Pauchet
Author-email: remi.pauchet@stormshield.eu
License: Apache License 2.0
Platform: UNKNOWN
Classifier: Programming Language :: Python :: 3
Classifier: Programming Language :: Python :: 3.7
Classifier: License :: OSI Approved :: Apache Software License
Classifier: Operating System :: OS Independent
Classifier: Topic :: System :: Networking
Classifier: Environment :: Console
License-File: LICENCE
Requires-Dist: colorlog
Requires-Dist: defusedxml
Requires-Dist: packaging
Requires-Dist: pygments
Requires-Dist: requests[socks]
Requires-Dist: requests-toolbelt
Requires-Dist: pyreadline ; platform_system == "Windows"
